README.rst
setup.cfg
setup.py
cmreslogging/__init__.py
cmreslogging/handlers.py
cmreslogging/serializers.py
spoke_CMRESHandler.egg-info/PKG-INFO
spoke_CMRESHandler.egg-info/SOURCES.txt
spoke_CMRESHandler.egg-info/dependency_links.txt
spoke_CMRESHandler.egg-info/requires.txt
spoke_CMRESHandler.egg-info/top_level.txt
tests/__init__.py
tests/test_cmreshandler.py
tests/test_cmresserializer.py